dataclasses_json/__init__.py
dataclasses_json/api.py
dataclasses_json/cfg.py
dataclasses_json/core.py
dataclasses_json/mm.py
dataclasses_json/py.typed
dataclasses_json/stringcase.py
dataclasses_json/undefined.py
dataclasses_json/utils.py
dataclasses_json-0.5.9.data/scripts/publish.py
dataclasses_json-0.5.9.dist-info/LICENSE
dataclasses_json-0.5.9.dist-info/METADATA
dataclasses_json-0.5.9.dist-info/WHEEL
dataclasses_json-0.5.9.dist-info/top_level.txt
dataclasses_json-0.5.9.dist-info/RECORD
