Metadata-Version: 2.1
Name: dataclasses-json
Version: 0.5.9
Summary: Easily serialize dataclasses to and from JSON
Home-page: https://github.com/lidatong/dataclasses-json
Author: lidatong
Author-email: charles.dt.li@gmail.com
License: MIT
Keywords: dataclasses json
Requires-Python: >=3.6
Provides-Extra: dev
License-File: LICENSE
